dothttp.py
dothttp-1.3.0.dist-info/METADATA
dothttp-1.3.0.dist-info/WHEEL
dothttp-1.3.0.dist-info/entry_points.txt
dothttp-1.3.0.dist-info/top_level.txt
dothttp-1.3.0.dist-info/RECORD
