Metadata-Version: 2.1
Name: dothttp
Version: 1.3.0
Summary: See https://github.com/tonsV2/dothttp
Home-page: UNKNOWN
License: UNKNOWN
Platform: UNKNOWN
Requires-Python: >=3
Requires-Dist: click
Requires-Dist: pygments
Requires-Dist: termcolor
